trade/__init__.py
trade/context.py
trade/holder.py
trade/occurrence.py
trade/subject.py
trade-1.1.4.dist-info/DESCRIPTION.rst
trade-1.1.4.dist-info/METADATA
trade-1.1.4.dist-info/RECORD
trade-1.1.4.dist-info/WHEEL
trade-1.1.4.dist-info/metadata.json
trade-1.1.4.dist-info/top_level.txt
