Metadata-Version: 2.0
Name: trade
Version: 1.1.4
Summary: A framework for financial applications.
Home-page: https://github.com/rochars/trade
Author: Rafael da Silva Rocha
Author-email: rocha.rafaelsilva@gmail.com
License: MIT
Keywords: asset stock exchange securities market finance investment money currency cost framework
Platform: UNKNOWN
Classifier: Development Status :: 5 - Production/Stable
Classifier: Intended Audience :: Developers
Classifier: Topic :: Software Development
Classifier: License :: OSI Approved :: MIT License
Classifier: Programming Language :: Python :: 2.7
Classifier: Programming Language :: Python :: 3.3
Classifier: Programming Language :: Python :: 3.4
Classifier: Programming Language :: Python :: 3.5
Classifier: Programming Language :: Python :: 3.6
